odoo/addons/base_search_multi/README.rst
odoo/addons/base_search_multi/__init__.py
odoo/addons/base_search_multi/__manifest__.py
odoo/addons/base_search_multi/i18n/base_search_multi.pot
odoo/addons/base_search_multi/models/__init__.py
odoo/addons/base_search_multi/models/models.py
odoo/addons/base_search_multi/readme/CONTRIBUTORS.rst
odoo/addons/base_search_multi/readme/DESCRIPTION.rst
odoo/addons/base_search_multi/readme/USAGE.rst
odoo/addons/base_search_multi/static/description/icon.png
odoo/addons/base_search_multi/static/description/index.html
odoo/addons/base_search_multi/tests/__init__.py
odoo/addons/base_search_multi/tests/test_search_multi.py
odoo13_addon_base_search_multi-13.0.1.0.1.dev2.dist-info/METADATA
odoo13_addon_base_search_multi-13.0.1.0.1.dev2.dist-info/WHEEL
odoo13_addon_base_search_multi-13.0.1.0.1.dev2.dist-info/top_level.txt
odoo13_addon_base_search_multi-13.0.1.0.1.dev2.dist-info/RECORD
